infrastructure_diagrams/__init__.py
infrastructure_diagrams/color.py
infrastructure_diagrams/enums.py
infrastructure_diagrams/graph.py
infrastructure_diagrams/settings.py
infrastructure_diagrams/utils.py
infrastructure_diagrams-0.0.6.data/scripts/infrastructure-diagrams
infrastructure_diagrams-0.0.6.dist-info/LICENSE.txt
infrastructure_diagrams-0.0.6.dist-info/METADATA
infrastructure_diagrams-0.0.6.dist-info/WHEEL
infrastructure_diagrams-0.0.6.dist-info/top_level.txt
infrastructure_diagrams-0.0.6.dist-info/RECORD
