Metadata-Version: 2.1
Name: infrastructure-diagrams
Version: 0.0.6
Summary: Create infrastructure diagrams from configuration files (YAML and JSON) by using Graphviz
Home-page: https://github.com/kotlarz/infrastructure-diagrams
Author: Marius Kotlarz
Author-email: marius@kotlarz.no
License: UNKNOWN
Platform: UNKNOWN
Classifier: Environment :: Console
Classifier: Development Status :: 3 - Alpha
Classifier: Intended Audience :: Developers
Classifier: Intended Audience :: System Administrators
Classifier: License :: OSI Approved :: MIT License
Classifier: Operating System :: OS Independent
Classifier: Programming Language :: Python :: 3 :: Only
Classifier: Programming Language :: Python :: 3.6
Classifier: Programming Language :: Python :: 3.7
Classifier: Programming Language :: Python :: 3.8
Classifier: Topic :: Documentation
Classifier: Topic :: Internet
Classifier: Topic :: Software Development :: Documentation
Classifier: Topic :: Utilities
Requires-Python: >=3.6
Requires-Dist: graphviz (>=0.13.2)
Requires-Dist: PyYAML (>=5.2)
Requires-Dist: python-magic (>=0.4.15)
Requires-Dist: colour (>=0.1.5)
Requires-Dist: SecretColors (>=1.1.0)
